{"stats":{"minecraft:custom":{"minecraft:mob_kills":4,"minecraft:interact_with_crafting_table":4,"minecraft:play_one_minute":86097,"minecraft:leave_game":1,"minecraft:time_since_death":93,"minecraft:sleep_in_bed":1,"minecraft:climb_one_cm":5437,"minecraft:time_since_rest":119,"minecraft:sprint_one_cm":51360,"minecraft:damage_taken":8277,"minecraft:walk_one_cm":251120,"minecraft:drop":21,"minecraft:damage_dealt":1905,"minecraft:swim_one_cm":203959,"minecraft:fly_one_cm":83191,"minecraft:open_chest":62,"minecraft:crouch_one_cm":35237,"minecraft:sneak_time":4595,"minecraft:deaths":24,"minecraft:walk_under_water_one_cm":86432,"minecraft:boat_one_cm":122857,"minecraft:jump":419,"minecraft:walk_on_water_one_cm":140628,"minecraft:fall_one_cm":7168},"minecraft:killed_by":{"minecraft:player":1,"mineminenomi:fighting_fish":1,"mineminenomi:marine_grunt":2,"mineminenomi:pirate_brute":2,"mineminenomi:pirate_captain":3,"mineminenomi:marine_sniper":1,"minecraft:drowned":1,"mineminenomi:pirate_grunt":11,"bonesandswords:key_keeper_skeleton":1,"bonesandswords:drowned_pirate":1},"minecraft:mined":{"minecraft:dark_prismarine":1,"minecraft:gray_stained_glass_pane":1,"minecraft:jungle_planks":2,"minecraft:sponge":2,"minecraft:chest":3,"minecraft:dead_bush":1,"minecraft:light_gray_bed":1,"minecraft:glass":1,"minecraft:oak_planks":10,"minecraft:spruce_stairs":1,"mineminenomi:wanted_poster_package":2,"minecraft:stripped_dark_oak_wood":2,"minecraft:cyan_concrete":1,"minecraft:dirt":1,"minecraft:sand":1},"minecraft:crafted":{"minecraft:crafting_table":1,"minecraft:iron_helmet":1,"minecraft:iron_boots":1,"minecraft:iron_chestplate":1,"minecraft:iron_ingot":3,"minecraft:iron_leggings":1,"minecraft:dark_oak_planks":8},"minecraft:picked_up":{"mineminenomi:cannon_ball":2,"minecraft:sponge":3,"oldguns:caplock_mechanism":1,"mineminenomi:key":2,"minecraft:crafting_table":7,"minecraft:iron_chestplate":7,"minecraft:wheat":21,"mineminenomi:tangerine":4,"minecraft:cooked_beef":99,"minecraft:ladder":2,"minecraft:golden_carrot":4,"minecraft:suspicious_stew":4,"minecraft:leather_leggings":1,"minecraft:wooden_pickaxe":7,"minecraft:potato":5,"minecraft:acacia_wood":1,"minecraft:oak_stairs":1,"minecraft:mushroom_stew":12,"minecraft:stripped_spruce_wood":1,"mineminenomi:cannon":5,"minecraft:shield":4,"minecraft:gunpowder":1,"mineminenomi:belly_pouch":4,"minecraft:map":4,"minecraft:string":7,"minecraft:dirt":1,"minecraft:paper":43,"mineminenomi:kairoseki_bullet":8,"minecraft:iron_axe":10,"minecraft:apple":8,"minecraft:beetroot_soup":16,"minecraft:iron_leggings":2,"minecraft:white_carpet":1,"minecraft:glass":1,"minecraft:bone":42,"minecraft:cyan_carpet":2,"minecraft:kelp":9,"minecraft:bow":4,"minecraft:gold_nugget":152,"minecraft:iron_ingot":23,"minecraft:stone_pickaxe":1,"minecraft:stripped_oak_wood":2,"minecraft:iron_nugget":13,"minecraft:iron_pickaxe":2,"minecraft:spruce_slab":8,"mineminenomi:axe":4,"minecraft:cyan_concrete":2,"minecraft:chest":18,"minecraft:iron_sword":2,"minecraft:oak_planks":131,"mineminenomi:flintlock":2,"minecraft:spruce_trapdoor":24,"minecraft:iron_boots":6,"mineminenomi:bullet":60,"minecraft:oak_slab":1,"oldguns:matchlock_arquebus":2,"minecraft:bowl":15,"minecraft:acacia_log":6,"minecraft:jungle_planks":7,"minecraft:spruce_stairs":9,"minecraft:birch_stairs":4,"minecraft:sand":1,"minecraft:dried_kelp":102,"aquaculture:red_grouper":1,"minecraft:spruce_log":18,"mineminenomi:dagger":1,"minecraft:dark_prismarine":1,"minecraft:stone_axe":11,"minecraft:light_gray_bed":1,"minecraft:arrow":5,"minecraft:rotten_flesh":29,"minecraft:iron_helmet":6,"minecraft:stripped_dark_oak_wood":2,"minecraft:bread":70,"minecraft:emerald":6,"minecraft:stripped_birch_wood":4,"mineminenomi:cutlass":5,"minecraft:coal":144,"minecraft:birch_log":1},"minecraft:used":{"minecraft:stone_sword":6,"minecraft:oak_planks":64,"minecraft:ladder":2,"minecraft:chest":5,"minecraft:shield":13,"minecraft:iron_sword":2,"mineminenomi:cutlass":48,"minecraft:dirt":1,"minecraft:sand":3,"mineminenomi:dagger":5,"minecraft:crafting_table":1,"minecraft:jungle_planks":1,"minecraft:mushroom_stew":2,"minecraft:spruce_stairs":6,"minecraft:sponge":2,"minecraft:glass":1,"minecraft:dark_oak_planks":8,"minecraft:apple":3,"minecraft:iron_axe":10,"minecraft:string":1,"minecraft:suspicious_stew":2,"minecraft:iron_pickaxe":8,"minecraft:jungle_stairs":1,"minecraft:cyan_concrete":1,"minecraft:fishing_rod":4,"minecraft:stone_axe":48,"minecraft:bow":6,"minecraft:golden_carrot":2,"alexsmobs:animal_dictionary":1,"minecraft:cooked_beef":6,"minecraft:light_gray_bed":1,"minecraft:birch_stairs":2},"minecraft:killed":{"mineminenomi:pirate_grunt":3,"mineminenomi:pirate_brute":1,"minecraft:drowned":1},"minecraft:dropped":{"minecraft:iron_sword":1,"minecraft:kelp":3,"mineminenomi:flintlock":1,"alexsmobs:animal_dictionary":1,"mineminenomi:cannon_ball":2,"minecraft:bowl":1,"mineminenomi:bullet":5,"minecraft:iron_helmet":1,"minecraft:rotten_flesh":5,"minecraft:iron_boots":1,"minecraft:spruce_door":1,"minecraft:suspicious_stew":1,"minecraft:iron_chestplate":1,"minecraft:map":2,"minecraft:gold_nugget":3,"minecraft:iron_axe":1,"minecraft:cyan_concrete":1,"minecraft:stone_pickaxe":1,"minecraft:wooden_pickaxe":1,"minecraft:stripped_oak_wood":2}},"DataVersion":2586}